protobuf2arr/__init__.py
protobuf2arr/nullable.proto
protobuf2arr/serializer.py
protobuf2arr-0.1.4.dist-info/LICENSE
protobuf2arr-0.1.4.dist-info/WHEEL
protobuf2arr-0.1.4.dist-info/METADATA
protobuf2arr-0.1.4.dist-info/RECORD
